odoo/addons/l10n_it_intrastat_statement/README.rst
odoo/addons/l10n_it_intrastat_statement/__init__.py
odoo/addons/l10n_it_intrastat_statement/__manifest__.py
odoo/addons/l10n_it_intrastat_statement/data/sequence.xml
odoo/addons/l10n_it_intrastat_statement/i18n/es.po
odoo/addons/l10n_it_intrastat_statement/i18n/it.po
odoo/addons/l10n_it_intrastat_statement/i18n/l10n_it_intrastat_statement.pot
odoo/addons/l10n_it_intrastat_statement/models/__init__.py
odoo/addons/l10n_it_intrastat_statement/models/config.py
odoo/addons/l10n_it_intrastat_statement/models/intrastat_statement.py
odoo/addons/l10n_it_intrastat_statement/models/intrastat_statement_purchase_section.py
odoo/addons/l10n_it_intrastat_statement/models/intrastat_statement_purchase_section1.py
odoo/addons/l10n_it_intrastat_statement/models/intrastat_statement_purchase_section2.py
odoo/addons/l10n_it_intrastat_statement/models/intrastat_statement_purchase_section3.py
odoo/addons/l10n_it_intrastat_statement/models/intrastat_statement_purchase_section4.py
odoo/addons/l10n_it_intrastat_statement/models/intrastat_statement_sale_section.py
odoo/addons/l10n_it_intrastat_statement/models/intrastat_statement_sale_section1.py
odoo/addons/l10n_it_intrastat_statement/models/intrastat_statement_sale_section2.py
odoo/addons/l10n_it_intrastat_statement/models/intrastat_statement_sale_section3.py
odoo/addons/l10n_it_intrastat_statement/models/intrastat_statement_sale_section4.py
odoo/addons/l10n_it_intrastat_statement/models/intrastat_statement_section.py
odoo/addons/l10n_it_intrastat_statement/readme/CONTRIBUTORS.md
odoo/addons/l10n_it_intrastat_statement/readme/DESCRIPTION.md
odoo/addons/l10n_it_intrastat_statement/readme/USAGE.md
odoo/addons/l10n_it_intrastat_statement/report/intrastat_mod1_bis.xml
odoo/addons/l10n_it_intrastat_statement/report/intrastat_mod1_ter.xml
odoo/addons/l10n_it_intrastat_statement/report/report_intrastat_mod1.xml
odoo/addons/l10n_it_intrastat_statement/report/report_intrastat_mod1_quater.xml
odoo_addon_l10n_it_intrastat_statement-18.0.1.0.0.2.dist-info/METADATA
odoo_addon_l10n_it_intrastat_statement-18.0.1.0.0.2.dist-info/WHEEL
odoo_addon_l10n_it_intrastat_statement-18.0.1.0.0.2.dist-info/top_level.txt
odoo_addon_l10n_it_intrastat_statement-18.0.1.0.0.2.dist-info/RECORD
